lowcode_code/__init__.py
lowcode_code/cli.py
lowcode_code/commands/__init__.py
lowcode_code/commands/render.py
lowcode_code/jinja.py
lowcode_code/render.py
lowcode_code/schema.py
lowcode_code/settings.py
lowcode_code/settings.yaml
lowcode_code-0.0.1.dist-info/LICENSE
lowcode_code-0.0.1.dist-info/METADATA
lowcode_code-0.0.1.dist-info/WHEEL
lowcode_code-0.0.1.dist-info/entry_points.txt
lowcode_code-0.0.1.dist-info/RECORD
